LICENSE
MANIFEST.in
README.md
setup.py
cabinet_structure/__init__.py
cabinet_structure/settings.py
cabinet_structure/views.py
cabinet_structure/static/cabinetmaps/css/bootstrap.min.css
cabinet_structure/static/cabinetmaps/css/cabinet_style.css
cabinet_structure/static/cabinetmaps/css/cabinet_style.css.map
cabinet_structure/static/cabinetmaps/img/idc-rack-42u.gif
cabinet_structure/static/cabinetmaps/js/bootstrap.min.js
cabinet_structure/static/cabinetmaps/sass/cabinet_style.scss
cabinet_structure/static/cabinetmaps/sass/.sass-cache/7c134596186e4fcdf89ae8fbfa73e7d299818287/cabinet_style.scssc
cabinet_structure/static/cabinetmaps/sass/.sass-cache/b3ab845fbfd709757aafdcd5e7f9224a4e2c45b4/cabinet_style.scssc
cabinet_structure/utils/__init__.py
cabinet_structure/utils/algorithm.py
cabinet_structure/utils/handle.py
cabinet_structure/utils/tools.py
django_dynamic_cabinetmaps.egg-info/PKG-INFO
django_dynamic_cabinetmaps.egg-info/SOURCES.txt
django_dynamic_cabinetmaps.egg-info/dependency_links.txt
django_dynamic_cabinetmaps.egg-info/top_level.txt
docs/Makefile
docs/make.bat
docs/.idea/.name
docs/.idea/doc.iml
docs/.idea/misc.xml
docs/.idea/modules.xml
docs/.idea/vcs.xml
docs/.idea/workspace.xml
docs/build/doctrees/author.doctree
docs/build/doctrees/changelog.doctree
docs/build/doctrees/environment.pickle
docs/build/doctrees/future.doctree
docs/build/doctrees/index.doctree
docs/build/doctrees/installation.doctree
docs/build/doctrees/sass.doctree
docs/build/doctrees/stylesheet.doctree
docs/build/doctrees/support.doctree
docs/build/doctrees/usage.doctree
docs/build/html/.buildinfo
docs/build/html/author.html
docs/build/html/changelog.html
docs/build/html/future.html
docs/build/html/genindex.html
docs/build/html/index.html
docs/build/html/installation.html
docs/build/html/objects.inv
docs/build/html/sass.html
docs/build/html/search.html
docs/build/html/searchindex.js
docs/build/html/stylesheet.html
docs/build/html/support.html
docs/build/html/usage.html
docs/build/html/_sources/author.txt
docs/build/html/_sources/changelog.txt
docs/build/html/_sources/future.txt
docs/build/html/_sources/index.txt
docs/build/html/_sources/installation.txt
docs/build/html/_sources/sass.txt
