Metadata-Version: 1.1
Name: django-dynamic-cabinetmaps
Version: 0.1.dev2
Summary: A lightweight dynamic create cabinet graph with django.
Home-page: https://github.com/boylegu/django-dynamic-cabinetmaps
Author: BoyleGu
Author-email: gubaoer@hotmail.com
License: MIT License
Platform: UNKNOWN
Classifier: Environment :: Web Environment
Classifier: Framework :: Django
Classifier: Framework :: Django :: 1.6
Classifier: Framework :: Django :: 1.7
Classifier: Framework :: Django :: 1.8
Classifier: Intended Audience :: Developers
Classifier: License :: OSI Approved :: MIT License
Classifier: Operating System :: OS Independent
Classifier: Programming Language :: Python
Classifier: Programming Language :: Python :: 2
Classifier: Programming Language :: Python :: 2.7
Classifier: Topic :: Internet :: WWW/HTTP
Classifier: Topic :: Internet :: WWW/HTTP :: Dynamic Content
